twitchview/__init__.py
twitchview/config.ini.example
twitchview/icon.ico
twitchview/icon.xbm
twitchview/irc.py
twitchview/main.py
twitchview-0.6.8.dist-info/LICENSE.txt
twitchview-0.6.8.dist-info/METADATA
twitchview-0.6.8.dist-info/WHEEL
twitchview-0.6.8.dist-info/entry_points.txt
twitchview-0.6.8.dist-info/top_level.txt
twitchview-0.6.8.dist-info/RECORD
