Metadata-Version: 2.1
Name: twitchview
Version: 0.6.8
Summary: Simple program by python for watching favorite twitch channels
Home-page: https://gitlab.com/aspellip/twitchview
Author: Aspel
Author-email: aspel@ukr.net
License: GPLv3
Keywords: twitch
Platform: UNKNOWN
Classifier: License :: OSI Approved :: GNU General Public License v3 or later (GPLv3+)
Classifier: Operating System :: POSIX
Classifier: Operating System :: MacOS :: MacOS X
Classifier: Operating System :: Microsoft :: Windows
Classifier: Programming Language :: Python :: 3
Classifier: Topic :: Internet :: WWW/HTTP
Classifier: Topic :: Multimedia :: Sound/Audio
Classifier: Topic :: Multimedia :: Video
Classifier: Topic :: Utilities
Requires-Python: >=3
Requires-Dist: m3u8
Requires-Dist: Pillow
